{"meta":{"generatedFrom":"github.com/Rendererrr/gtaDiscoveryApi","cdnBase":"https://cdn.jsdelivr.net/gh/Rendererrr/gtaDiscoveryApi@main","rawBase":"https://raw.githubusercontent.com/Rendererrr/gtaDiscoveryApi/main","domain":"objects","label":"Objects","note":"Flat catalog of GTA object/prop models. hash = joaat(id). Curated objects carry a display `name` + `category` (known: true); the rest have name === id and category: null. No images. index.json is compact due to size; per-category slices live under by-category/."},"group":{"name":"Beach","slug":"beach","count":34},"count":34,"items":[{"id":"prop_beach_bbq","name":"Beach BBQ","hash":2686273380,"category":"Beach","known":true},{"id":"prop_beach_fire","name":"Beach Fire","hash":3229200997,"category":"Beach","known":true},{"id":"prop_beach_lg_float","name":"Beach Large Float","hash":2414194749,"category":"Beach","known":true},{"id":"prop_beach_lilo_01","name":"Lilo","hash":1715961520,"category":"Beach","known":true},{"id":"prop_beach_lilo_02","name":"Beach Lilo #2","hash":2619173467,"category":"Beach","known":true},{"id":"prop_beach_lotion_01","name":"Sun Lotion #1","hash":3740697263,"category":"Beach","known":true},{"id":"prop_beach_lotion_02","name":"Sun Lotion #2","hash":238248232,"category":"Beach","known":true},{"id":"prop_beach_lotion_03","name":"Sun Lotion #3","hash":2468375312,"category":"Beach","known":true},{"id":"prop_beach_parasol_01","name":"Beach Parasol #1","hash":1054627099,"category":"Beach","known":true},{"id":"prop_beach_parasol_02","name":"Beach Parasol #2","hash":756855196,"category":"Beach","known":true},{"id":"prop_beach_parasol_04","name":"Beach Parasol #3","hash":2365747570,"category":"Beach","known":true},{"id":"prop_beach_parasol_09","name":"Beach Parasol #4","hash":3143749168,"category":"Beach","known":true},{"id":"prop_beach_parasol_10","name":"Beach Parasol #5","hash":1483509531,"category":"Beach","known":true},{"id":"prop_beach_ring_01","name":"Rubber Ring","hash":1677315747,"category":"Beach","known":true},{"id":"prop_beach_rings_01","name":"Rubber Rings","hash":1772442022,"category":"Beach","known":true},{"id":"prop_beach_sandcas_01","name":"Sandcastle #1","hash":336523661,"category":"Beach","known":true},{"id":"prop_beach_sandcas_03","name":"Sandcastle #2","hash":339341791,"category":"Beach","known":true},{"id":"prop_beach_sandcas_04","name":"Sandcastle #3","hash":1285350052,"category":"Beach","known":true},{"id":"prop_beach_sandcas_05","name":"Sandcastle #4","hash":3806138150,"category":"Beach","known":true},{"id":"prop_beach_towel_01","name":"Beach Towel #4","hash":1181350742,"category":"Beach","known":true},{"id":"prop_beach_towel_02","name":"Beach Towel #2","hash":951345131,"category":"Beach","known":true},{"id":"prop_beach_towel_03","name":"Beach Towel #3","hash":1604201946,"category":"Beach","known":true},{"id":"prop_beachball_01","name":"Beach Ball","hash":1574107526,"category":"Beach","known":true},{"id":"prop_beachf_01_cr","name":"Beach Flag","hash":1275920395,"category":"Beach","known":true},{"id":"prop_beachflag_01","name":"Beach Flagpole #1","hash":3530712543,"category":"Beach","known":true},{"id":"prop_beachflag_02","name":"Beach Flagpole #2","hash":1585741317,"category":"Beach","known":true},{"id":"prop_buck_spade_01","name":"Bucket & Spade #1","hash":1678716578,"category":"Beach","known":true},{"id":"prop_buck_spade_02","name":"Bucket & Spade #2","hash":1909574183,"category":"Beach","known":true},{"id":"prop_buck_spade_05","name":"Bucket & Spade #3","hash":2791650125,"category":"Beach","known":true},{"id":"prop_buck_spade_08","name":"Bucket & Spade #4","hash":1353058256,"category":"Beach","known":true},{"id":"prop_buck_spade_09","name":"Bucket & Spade #5","hash":4068232086,"category":"Beach","known":true},{"id":"prop_byard_lifering","name":"Life Ring #2","hash":3238044290,"category":"Beach","known":true},{"id":"prop_cs_beachtowel_01","name":"Beach Towel #1","hash":1280564504,"category":"Beach","known":true},{"id":"prop_life_ring_02","name":"Life Ring #1","hash":2988419552,"category":"Beach","known":true}]}