{"meta":{"generatedFrom":"github.com/Rendererrr/gtaDiscoveryApi","cdnBase":"https://cdn.jsdelivr.net/gh/Rendererrr/gtaDiscoveryApi@main","rawBase":"https://raw.githubusercontent.com/Rendererrr/gtaDiscoveryApi/main","domain":"particles","label":"Particles","note":"Flat catalog of particle (PTFX) effects. A particle is a (dict, effect) pair: REQUEST_NAMED_PTFX_ASSET(dict) then START_PARTICLE_FX_*(effect). category = dictionary. Curated effects carry a friendly name (curated: true); the rest have name === effect. No images, no hash. index.json is compact; per-dictionary slices live under by-category/."},"group":{"name":"ent_hr_rob_whistle","slug":"ent-hr-rob-whistle","count":1},"count":1,"items":[{"id":"ent_hr_rob_whistle/ent_amb_hr_rob_vault_gas_leak","name":"ent_amb_hr_rob_vault_gas_leak","dict":"ent_hr_rob_whistle","effect":"ent_amb_hr_rob_vault_gas_leak","category":"ent_hr_rob_whistle","curated":false}]}